dokku_api/.env.sample
dokku_api/Dockerfile
dokku_api/LICENSE
dokku_api/Makefile
dokku_api/Procfile
dokku_api/README.md
dokku_api/__init__.py
dokku_api/cli.py
dokku_api/docker-compose.yml
dokku_api/poetry.lock
dokku_api/pyproject.toml
dokku_api/src/__main__.py
dokku_api/src/api/app.py
dokku_api/src/api/middlewares/__init__.py
dokku_api/src/api/middlewares/session.py
dokku_api/src/api/models/__init__.py
dokku_api/src/api/models/app.py
dokku_api/src/api/models/base.py
dokku_api/src/api/models/models.py
dokku_api/src/api/models/network.py
dokku_api/src/api/models/resource.py
dokku_api/src/api/models/service.py
dokku_api/src/api/models/shared_app.py
dokku_api/src/api/models/user.py
dokku_api/src/api/router/__init__.py
dokku_api/src/api/router/admin/__init__.py
dokku_api/src/api/router/admin/api.py
dokku_api/src/api/router/admin/apps.py
dokku_api/src/api/router/admin/letsencrypt.py
dokku_api/src/api/router/admin/plugins.py
dokku_api/src/api/router/admin/resources.py
dokku_api/src/api/router/admin/router.py
dokku_api/src/api/router/admin/users.py
dokku_api/src/api/router/api.py
dokku_api/src/api/router/apps.py
dokku_api/src/api/router/base.py
dokku_api/src/api/router/config.py
dokku_api/src/api/router/databases.py
dokku_api/src/api/router/domains.py
dokku_api/src/api/router/git.py
dokku_api/src/api/router/letsencrypt.py
dokku_api/src/api/router/networks.py
dokku_api/src/api/router/quota.py
dokku_api/src/api/router/router.py
dokku_api/src/api/router/search.py
dokku_api/src/api/router/ssh.py
dokku_api/src/api/router/upload.py
dokku_api/src/api/schemas/__init__.py
dokku_api/src/api/schemas/user.py
dokku_api/src/api/services/__init__.py
dokku_api/src/api/services/apps.py
dokku_api/src/api/services/config.py
dokku_api/src/api/services/databases.py
dokku_api/src/api/services/domains.py
dokku_api/src/api/services/git.py
dokku_api/src/api/services/letsencrypt.py
dokku_api/src/api/services/networks.py
dokku_api/src/api/services/plugins.py
dokku_api/src/api/tools/__init__.py
dokku_api-1.2.8.dist-info/METADATA
dokku_api-1.2.8.dist-info/WHEEL
dokku_api-1.2.8.dist-info/entry_points.txt
dokku_api-1.2.8.dist-info/licenses/LICENSE
dokku_api-1.2.8.dist-info/RECORD
