Metadata-Version: 2.4
Name: dokku-api
Version: 1.2.8
Summary: A RESTful API for managing applications and resources on a Dokku platform.
License: MIT
License-File: LICENSE
Keywords: dokku,api,paas,application,deployment,devops,automation
Author: JeanExtreme002
Author-email: jeanextreme002@gmail.com
Requires-Python: >=3.11
Classifier: License :: OSI Approved :: MIT License
Classifier: Intended Audience :: Developers
Classifier: Operating System :: POSIX :: Linux
Classifier: Programming Language :: Python :: 3 :: Only
Classifier: Programming Language :: Python :: 3.11
Classifier: Programming Language :: Python :: 3.12
Classifier: Topic :: Scientific/Engineering
Classifier: Topic :: Security
Classifier: Topic :: System :: Systems Administration
Requires-Dist: PyNaCl (==1.5.0)
Requires-Dist: PyYAML (==6.0)
Requires-Dist: aiofiles (>=24.1.0)
Requires-Dist: aiomysql (>=0.2.0)
Requires-Dist: anyio (==3.5.0)
Requires-Dist: apscheduler (>=3.11.2,<4.0.0)
Requires-Dist: asgiref (==3.5.0)
Requires-Dist: asyncmy (>=0.2.10)
Requires-Dist: asyncssh (==2.13.2)
Requires-Dist: bcrypt (==3.2.0)
Requires-Dist: cffi (==1.15.0)
Requires-Dist: click (==8.0.4)
Requires-Dist: colorama (==0.4.4)
Requires-Dist: cryptography (==36.0.1)
Requires-Dist: fastapi (==0.75.0)
Requires-Dist: greenlet (>=3.2.4,<4.0.0)
Requires-Dist: h11 (==0.13.0)
Requires-Dist: httptools (==0.6.4)
Requires-Dist: httpx (>=0.28.1)
Requires-Dist: idna (==3.3)
Requires-Dist: pycparser (==2.21)
Requires-Dist: pydantic (==1.10)
Requires-Dist: pymysql (>=1.1.1)
Requires-Dist: python-decouple (==3.6)
Requires-Dist: python-dotenv (==0.19.2)
Requires-Dist: python-multipart (==0.0.5)
Requires-Dist: requests (>=2.32.3)
Requires-Dist: six (==1.16.0)
Requires-Dist: sniffio (==1.2.0)
Requires-Dist: sqlalchemy (>=2.0.41)
Requires-Dist: starlette (==0.17.1)
Requires-Dist: typing_extensions (==4.6.0)
Requires-Dist: uvicorn (==0.17.5)
Requires-Dist: watchgod (==0.7)
Requires-Dist: websockets (==10.2)
Project-URL: Documentation, https://github.com/JeanExtreme002/dokku-api
Project-URL: Homepage, https://github.com/JeanExtreme002/dokku-api
Project-URL: Repository, https://github.com/JeanExtreme002/dokku-api
